setup.py
pipedrive/Pipedrive.py
pipedrive/__init__.py
pipedrive_python.egg-info/PKG-INFO
pipedrive_python.egg-info/SOURCES.txt
pipedrive_python.egg-info/dependency_links.txt
pipedrive_python.egg-info/requires.txt
pipedrive_python.egg-info/top_level.txt