Metadata-Version: 1.1
Name: pipedrive-python
Version: 0.0.1
Summary: Python library for interacting with the Pipedrive API.
Home-page: http://github.com/bellhops/pipedrive-python
Author: Anthony Blardo
Author-email: anthony@blar.do
License: MIT License
Platform: any
Classifier: Programming Language :: Python
Classifier: Development Status :: 2 - Pre-Alpha
Classifier: Natural Language :: English
Classifier: Environment :: Web Environment
Classifier: Intended Audience :: Developers
Classifier: Operating System :: OS Independent
Classifier: Topic :: Software Development :: Libraries :: Python Modules
Classifier: Topic :: Internet :: WWW/HTTP :: Dynamic Content
